[{"text": "if you were to be the president of this", "start": 0.16, "duration": 5.96}, {"text": "country what would you do differently I", "start": 2.639, "duration": 4.72}, {"text": "think the state of the nation is a", "start": 6.12, "duration": 2.76}, {"text": "reflection of the people not the leaders", "start": 7.359, "duration": 4.921}, {"text": "alone a bad people cannot get a good", "start": 8.88, "duration": 5.959}, {"text": "leader and most Nigerians are bad I", "start": 12.28, "duration": 5.159}, {"text": "don't think democracy is what is totally", "start": 14.839, "duration": 5.161}, {"text": "right for Nigeria people that can't sit", "start": 17.439, "duration": 5.041}, {"text": "down and think by themselves probably", "start": 20.0, "duration": 3.84}, {"text": "need someone to help them do the", "start": 22.48, "duration": 4.32}, {"text": "thinking Nigeria is so blessed I mean", "start": 23.84, "duration": 5.199}, {"text": "we've had the president that is dead he", "start": 26.8, "duration": 3.76}, {"text": "Piet even though he's dead", "start": 29.039, "duration": 4.881}, {"text": "still sending us money every time that's", "start": 30.56, "duration": 5.72}, {"text": "to tell you the vast wealth that is in", "start": 33.92, "duration": 4.92}, {"text": "this country every special edition of", "start": 36.28, "duration": 5.959}, {"text": "the SOS always comes with something new", "start": 38.84, "duration": 5.96}, {"text": "something fresh something uh remarkable", "start": 42.239, "duration": 6.361}, {"text": "something Sublime and this is not any", "start": 44.8, "duration": 6.279}, {"text": "different and we believe strongly that", "start": 48.6, "duration": 6.72}, {"text": "as you join this broadcast you will be", "start": 51.079, "duration": 6.441}, {"text": "able to participate even though you were", "start": 55.32, "duration": 4.0}, {"text": "not part of the people in the studio", "start": 57.52, "duration": 3.24}, {"text": "because it's very interactive is going", "start": 59.32, "duration": 4.079}, {"text": "to bring you answers to questions you", "start": 60.76, "duration": 5.039}, {"text": "don't even have an idea uh is bothering", "start": 63.399, "duration": 4.961}, {"text": "your heart so I want to take you to the", "start": 65.799, "duration": 5.0}, {"text": "studio where you'll join the people that", "start": 68.36, "duration": 6.16}, {"text": "joined us at the studio to present this", "start": 70.799, "duration": 10.381}, {"text": "edition of s special to you thank you", "start": 74.52, "duration": 16.619}, {"text": "[Music]", "start": 81.18, "duration": 9.959}, {"text": "okay so yes I would ask the questions", "start": 92.399, "duration": 4.801}, {"text": "together because they are related so um", "start": 94.479, "duration": 4.721}, {"text": "the question says it is amazing that a", "start": 97.2, "duration": 4.599}, {"text": "blessed Nation like Nigeria okay blessed", "start": 99.2, "duration": 5.12}, {"text": "Nation have nigerias who major on the", "start": 101.799, "duration": 6.081}, {"text": "minor and minor on the major okay and it", "start": 104.32, "duration": 6.839}, {"text": "looks some sometimes looks like um we we", "start": 107.88, "duration": 4.919}, {"text": "don't have a clue of our", "start": 111.159, "duration": 4.121}, {"text": "destination so as a nation yes as a", "start": 112.799, "duration": 5.32}, {"text": "nation yes okay the leaders we don't", "start": 115.28, "duration": 4.68}, {"text": "have a clue of they don't have a clue of", "start": 118.119, "duration": 5.441}, {"text": "Des of our destination so the question", "start": 119.96, "duration": 6.4}, {"text": "the first question is what roles should", "start": 123.56, "duration": 5.96}, {"text": "our ministers play in politics and", "start": 126.36, "duration": 6.32}, {"text": "governance apart from prayers then the", "start": 129.52, "duration": 7.68}, {"text": "second one is that you as our pastor um", "start": 132.68, "duration": 7.08}, {"text": "you have a you have an amazing portfolio", "start": 137.2, "duration": 5.48}, {"text": "in leadership and finance and um if you", "start": 139.76, "duration": 6.16}, {"text": "were to be the president of this country", "start": 142.68, "duration": 7.36}, {"text": "what would you do differently", "start": 145.92, "duration": 5.92}, {"text": "there I understand why you are saying", "start": 150.04, "duration": 3.12}, {"text": "maybe there be more question because", "start": 151.84, "duration": 4.0}, {"text": "this question is a long", "start": 153.16, "duration": 5.0}, {"text": "question first and foremost the role of", "start": 155.84, "duration": 4.319}, {"text": "the church yes that maybe our nation the", "start": 158.16, "duration": 4.64}, {"text": "leaders are clueless at times I we can", "start": 160.159, "duration": 4.401}, {"text": "be harsh on them but at times I also ask", "start": 162.8, "duration": 3.4}, {"text": "myself there are things we are see they", "start": 164.56, "duration": 3.52}, {"text": "are saying that we are not seeing so we", "start": 166.2, "duration": 4.399}, {"text": "must air on that side but having said", "start": 168.08, "duration": 3.92}, {"text": "that there are Basics that I still", "start": 170.599, "duration": 3.121}, {"text": "expect that they can do and when you see", "start": 172.0, "duration": 4.72}, {"text": "some of them do it then it doesn't", "start": 173.72, "duration": 4.439}, {"text": "exonerate the ones are not doing it", "start": 176.72, "duration": 3.2}, {"text": "there are some Governors that get into", "start": 178.159, "duration": 3.36}, {"text": "state where they say there's no money", "start": 179.92, "duration": 3.879}, {"text": "and they end up paying everybody not", "start": 181.519, "duration": 4.28}, {"text": "owing and still doing projects and you", "start": 183.799, "duration": 5.16}, {"text": "ask yourself who is feeling who but", "start": 185.799, "duration": 4.961}, {"text": "ultimately I think the state of the", "start": 188.959, "duration": 3.36}, {"text": "nation is a reflection of the people not", "start": 190.76, "duration": 4.92}, {"text": "the leaders alone a bad people cannot", "start": 192.319, "duration": 5.84}, {"text": "get a good leader and most Nigerians are", "start": 195.68, "duration": 4.72}, {"text": "bad you get to feeling station and it's", "start": 198.159, "duration": 3.8}, {"text": "not dis stealing because when you say", "start": 200.4, "duration": 3.04}, {"text": "bad now people will tell you I'm not", "start": 201.959, "duration": 3.521}, {"text": "Sten any money because you know they cat", "start": 203.44, "duration": 3.56}, {"text": "you you don't have anybody that you run", "start": 205.48, "duration": 4.0}, {"text": "to so not doesn't mean you don't have", "start": 207.0, "duration": 5.84}, {"text": "Ste Tendencies You probably just H know", "start": 209.48, "duration": 5.759}, {"text": "you not get away with it but how I will", "start": 212.84, "duration": 4.679}, {"text": "measure a good citizen you don't drive", "start": 215.239, "duration": 3.28}, {"text": "one", "start": 217.519, "duration": 3.201}, {"text": "way what I said i' never driv one way", "start": 218.519, "duration": 4.121}, {"text": "before people find it hard to believe", "start": 220.72, "duration": 3.439}, {"text": "except they've closed the road and they", "start": 222.64, "duration": 4.2}, {"text": "say we should pass here you go to", "start": 224.159, "duration": 5.401}, {"text": "filling stations that's how you know", "start": 226.84, "duration": 5.479}, {"text": "Nigerians are not good people somebody", "start": 229.56, "duration": 5.8}, {"text": "has been on queue for 3 hours he got", "start": 232.319, "duration": 7.64}, {"text": "there 500 a.m. now you you have uh don't", "start": 235.36, "duration": 6.84}, {"text": "even say Let me give this people money", "start": 239.959, "duration": 5.12}, {"text": "we will say okay you paid to enter paid", "start": 242.2, "duration": 5.679}, {"text": "entry no as they open the", "start": 245.079, "duration": 5.921}, {"text": "gates you just shook your head inside", "start": 247.879, "duration": 5.881}, {"text": "and because of you they stop selling", "start": 251.0, "duration": 5.32}, {"text": "until sanity thatan doesn't return they", "start": 253.76, "duration": 4.199}, {"text": "will not do you have not just destroyed", "start": 256.32, "duration": 3.039}, {"text": "somebody that spent 3", "start": 257.959, "duration": 3.96}, {"text": "hours because if you in a hurry have you", "start": 259.359, "duration": 4.161}, {"text": "considered it to they have a", "start": 261.919, "duration": 3.481}, {"text": "destination but if all of us stay at", "start": 263.52, "duration": 3.92}, {"text": "turn and people go abroad they join the", "start": 265.4, "duration": 4.04}, {"text": "line so how come when you get to your", "start": 267.44, "duration": 3.72}, {"text": "own line land you want to jump the queue", "start": 269.44, "duration": 4.88}, {"text": "it shows that you are a wicked person so", "start": 271.16, "duration": 5.12}, {"text": "as wicked as you are God is not going to", "start": 274.32, "duration": 3.24}, {"text": "look down and give you a leader that", "start": 276.28, "duration": 3.68}, {"text": "make your life better he has to allow", "start": 277.56, "duration": 5.32}, {"text": "because as the people are so are the", "start": 279.96, "duration": 4.76}, {"text": "leaders I mean they came out from", "start": 282.88, "duration": 4.159}, {"text": "amongus so we can't keep making it look", "start": 284.72, "duration": 4.199}, {"text": "like these people just descended from", "start": 287.039, "duration": 3.761}, {"text": "the from heaven or they emanated from", "start": 288.919, "duration": 4.161}, {"text": "the pit of Hell they your uncle they", "start": 290.8, "duration": 4.04}, {"text": "your brother I mean I've had cases of", "start": 293.08, "duration": 3.76}, {"text": "people tell their loved ones that became", "start": 294.84, "duration": 3.76}, {"text": "government officials that tell them I", "start": 296.84, "duration": 3.799}, {"text": "want to do it right say are you crazy", "start": 298.6, "duration": 3.879}, {"text": "say when it's our own time now you are", "start": 300.639, "duration": 3.201}, {"text": "saying that you're not giving contract", "start": 302.479, "duration": 3.401}, {"text": "to family you want to do it right you're", "start": 303.84, "duration": 5.079}, {"text": "against nepotism so let us chop our to", "start": 305.88, "duration": 4.92}, {"text": "it never finishes and that's how the", "start": 308.919, "duration": 4.84}, {"text": "cycle continues the RO of the church or", "start": 310.8, "duration": 6.64}, {"text": "the ministers is simple to raise better", "start": 313.759, "duration": 5.921}, {"text": "people if God is calling minister to", "start": 317.44, "duration": 4.96}, {"text": "politics I'm not going to debate that or", "start": 319.68, "duration": 4.32}, {"text": "I don't want I don't like controversial", "start": 322.4, "duration": 4.88}, {"text": "issues everybody hears differently I", "start": 324.0, "duration": 5.28}, {"text": "know there's no greater honor than to", "start": 327.28, "duration": 2.88}, {"text": "serve God", "start": 329.28, "duration": 3.039}, {"text": "so I'm not going to leave pastoring now", "start": 330.16, "duration": 4.56}, {"text": "to say I want to be president of Nigeria", "start": 332.319, "duration": 5.761}, {"text": "unless God tells me I should abandon", "start": 334.72, "duration": 6.16}, {"text": "pastoring some of our pastors are", "start": 338.08, "duration": 6.48}, {"text": "probably uh student union leaders ER", "start": 340.88, "duration": 6.879}, {"text": "radicals uh activist in their school", "start": 344.56, "duration": 6.28}, {"text": "days they get born again start serving", "start": 347.759, "duration": 5.16}, {"text": "God and that part of their life is still", "start": 350.84, "duration": 3.68}, {"text": "there so what they saying God is telling", "start": 352.919, "duration": 5.12}, {"text": "them may just be their old activism that", "start": 354.52, "duration": 5.6}, {"text": "is trying to find expression and if you", "start": 358.039, "duration": 4.761}, {"text": "want to leave poy to do that then it's", "start": 360.12, "duration": 5.32}, {"text": "fine I have no problem with that so far", "start": 362.8, "duration": 3.959}, {"text": "you and God have read clearly that's", "start": 365.44, "duration": 5.28}, {"text": "fine by me but in terms of their primary", "start": 366.759, "duration": 7.16}, {"text": "work the church ministers are to raise", "start": 370.72, "duration": 4.68}, {"text": "good Christians and how do you raise", "start": 373.919, "duration": 3.601}, {"text": "good Christians it is never by preaching", "start": 375.4, "duration": 3.359}, {"text": "20 minutes", "start": 377.52, "duration": 4.16}, {"text": "message it is never by conf not not you", "start": 378.759, "duration": 5.16}, {"text": "avoiding to confront what is wrong in", "start": 381.68, "duration": 4.68}, {"text": "name of not upsetting people it is not", "start": 383.919, "duration": 4.84}, {"text": "by all these humanistic messages that", "start": 386.36, "duration": 4.72}, {"text": "appeal to the flesh but they do nothing", "start": 388.759, "duration": 5.081}, {"text": "to the spirit is not by you telling", "start": 391.08, "duration": 5.679}, {"text": "somebody by any means necessary get", "start": 393.84, "duration": 7.28}, {"text": "money share this uh press the share", "start": 396.759, "duration": 7.801}, {"text": "button even if you're a secular artist", "start": 401.12, "duration": 8.56}, {"text": "use my song to H do a whatever and Link", "start": 404.56, "duration": 7.12}, {"text": "me you can't reach people it's just by", "start": 409.68, "duration": 5.0}, {"text": "saying I will H prove to you that acid", "start": 411.68, "duration": 4.88}, {"text": "can kill by drinking it I don't have to", "start": 414.68, "duration": 3.88}, {"text": "do that it the same I don't have to", "start": 416.56, "duration": 3.8}, {"text": "descend to that level to prove to you", "start": 418.56, "duration": 3.12}, {"text": "that God is good we don't lower the", "start": 420.36, "duration": 3.16}, {"text": "standard to maintain it we actually rais", "start": 421.68, "duration": 4.76}, {"text": "it for people to come up to it have you", "start": 423.52, "duration": 6.0}, {"text": "noticed and of late I I I did that I", "start": 426.44, "duration": 5.0}, {"text": "heard my father-in-law say it and I had", "start": 429.52, "duration": 4.16}, {"text": "to go and find out and I realized it was", "start": 431.44, "duration": 3.479}, {"text": "true", "start": 433.68, "duration": 6.04}, {"text": "between the 60s 70s and 80s 90s then", "start": 434.919, "duration": 8.12}, {"text": "from 2000 Below in fact 2002 what I saw", "start": 439.72, "duration": 5.479}, {"text": "was still all right from 2004 go and", "start": 443.039, "duration": 3.56}, {"text": "look at", "start": 445.199, "duration": 4.44}, {"text": "it to get into medicine in those days", "start": 446.599, "duration": 5.44}, {"text": "you need 300 and something but now it", "start": 449.639, "duration": 3.481}, {"text": "has come", "start": 452.039, "duration": 4.521}, {"text": "down and they realized that person that", "start": 453.12, "duration": 5.84}, {"text": "did research realized that the more they", "start": 456.56, "duration": 6.72}, {"text": "drop the cut off the more the children", "start": 458.96, "duration": 7.04}, {"text": "standards also comes down because God", "start": 463.28, "duration": 4.359}, {"text": "created standards originally as", "start": 466.0, "duration": 3.08}, {"text": "something that we should all aspire to", "start": 467.639, "duration": 4.12}, {"text": "attain to that's why you try to jump you", "start": 469.08, "duration": 4.6}, {"text": "all that all of us do jumping even at", "start": 471.759, "duration": 3.481}, {"text": "our level you know put stick and all", "start": 473.68, "duration": 4.04}, {"text": "that you know when they raise it up and", "start": 475.24, "duration": 3.959}, {"text": "your friend jump it I can't jump it I", "start": 477.72, "duration": 4.759}, {"text": "don't know about you I became po jumper", "start": 479.199, "duration": 5.881}, {"text": "just to prove nothing just to prove that", "start": 482.479, "duration": 4.4}, {"text": "D will not do this jump and I will not", "start": 485.08, "duration": 5.399}, {"text": "do it I jumping motivated me to want to", "start": 486.879, "duration": 5.241}, {"text": "and that's how standards are you raise", "start": 490.479, "duration": 5.56}, {"text": "it tell people now that to get into this", "start": 492.12, "duration": 7.24}, {"text": "program you need to score 350 and you", "start": 496.039, "duration": 5.56}, {"text": "are like the benefit you'll be", "start": 499.36, "duration": 5.04}, {"text": "shocked that they will get there but", "start": 501.599, "duration": 5.081}, {"text": "there no more standard so that's why a", "start": 504.4, "duration": 5.28}, {"text": "mad man can open church and start when", "start": 506.68, "duration": 5.839}, {"text": "the days of the fathers of Faith you", "start": 509.68, "duration": 5.64}, {"text": "have to think twice because to even get", "start": 512.519, "duration": 6.281}, {"text": "into their Fellowship money will open", "start": 515.32, "duration": 5.199}, {"text": "doors for you is your character that", "start": 518.8, "duration": 3.679}, {"text": "open doors for you but now you a", "start": 520.519, "duration": 3.281}, {"text": "criminal you start a church once you", "start": 522.479, "duration": 2.841}, {"text": "give offering offering offering offering", "start": 523.8, "duration": 3.68}, {"text": "you'll be accepted in some circles until", "start": 525.32, "duration": 4.0}, {"text": "you have problems and they deny you and", "start": 527.48, "duration": 3.88}, {"text": "I'm not trying to no I don't like all", "start": 529.32, "duration": 5.0}, {"text": "this church VOA I'm just giving examples", "start": 531.36, "duration": 4.64}, {"text": "you understand what I'm saying", "start": 534.32, "duration": 3.4}, {"text": "now", "start": 536.0, "duration": 6.839}, {"text": "so we have to get to that point where we", "start": 537.72, "duration": 8.239}, {"text": "make people understand what God expects", "start": 542.839, "duration": 6.201}, {"text": "from them as citizens of a Nation my", "start": 545.959, "duration": 5.12}, {"text": "book mod question Nation answers also", "start": 549.04, "duration": 3.52}, {"text": "ask that part nationhood is part of the", "start": 551.079, "duration": 3.721}, {"text": "questions I answered your role in a", "start": 552.56, "duration": 5.2}, {"text": "nation when you want to leave a nation", "start": 554.8, "duration": 6.159}, {"text": "and Ja not even become a sin when I", "start": 557.76, "duration": 6.519}, {"text": "wrote H when I did the manuscript of the", "start": 560.959, "duration": 5.761}, {"text": "book I just didn't release it uh that", "start": 564.279, "duration": 4.68}, {"text": "period because the other ones we wanted", "start": 566.72, "duration": 6.08}, {"text": "to release first so it's all there that", "start": 568.959, "duration": 5.641}, {"text": "is the I believe that the role of the", "start": 572.8, "duration": 4.84}, {"text": "church prayer We Can't Stop praying and", "start": 574.6, "duration": 4.44}, {"text": "the person said other than prayer We", "start": 577.64, "duration": 4.319}, {"text": "Can't Stop praying I don't have a", "start": 579.04, "duration": 5.359}, {"text": "sacrifice I can't kill human beings to", "start": 581.959, "duration": 4.641}, {"text": "appease any God his prayer I have so", "start": 584.399, "duration": 3.321}, {"text": "I'll pray in the morning I'll pray in", "start": 586.6, "duration": 2.799}, {"text": "the after I pray in the evening and I'll", "start": 587.72, "duration": 4.239}, {"text": "stand for the truth that I've believed", "start": 589.399, "duration": 5.201}, {"text": "in now if I have to be a leader in", "start": 591.959, "duration": 5.161}, {"text": "Nigeria I would want to be because I", "start": 594.6, "duration": 4.2}, {"text": "wanted to be as a military president now", "start": 597.12, "duration": 3.0}, {"text": "you're asking me person question I'm", "start": 598.8, "duration": 4.599}, {"text": "answering personally I don't think", "start": 600.12, "duration": 5.48}, {"text": "democracy is what is totally right for", "start": 603.399, "duration": 5.44}, {"text": "Nigeria I know when you uh I know people", "start": 605.6, "duration": 6.12}, {"text": "watching will have problems uh with it", "start": 608.839, "duration": 6.281}, {"text": "and all that it's it's fine whatever", "start": 611.72, "duration": 5.44}, {"text": "insult and whatever you want to put just", "start": 615.12, "duration": 3.48}, {"text": "be rest assured I will not give any", "start": 617.16, "duration": 3.28}, {"text": "answer to whatever comment you put but I", "start": 618.6, "duration": 5.08}, {"text": "will read it and laugh and enjoy it uh", "start": 620.44, "duration": 5.519}, {"text": "if people that can't sit down and think", "start": 623.68, "duration": 4.719}, {"text": "by themselves probably need someone to", "start": 625.959, "duration": 4.361}, {"text": "help them do the thinking the level of", "start": 628.399, "duration": 3.521}, {"text": "discipline we had when military was in", "start": 630.32, "duration": 2.8}, {"text": "charge it's not the same level of", "start": 631.92, "duration": 2.719}, {"text": "discipline that we have", "start": 633.12, "duration": 5.32}, {"text": "now I know people that weit late comers", "start": 634.639, "duration": 6.721}, {"text": "but the days of Di and state they", "start": 638.44, "duration": 4.92}, {"text": "started going to work early because if", "start": 641.36, "duration": 5.08}, {"text": "they catch you late you are going to be", "start": 643.36, "duration": 5.52}, {"text": "severely punished they made you read the", "start": 646.44, "duration": 4.48}, {"text": "national Anem that a lot of people", "start": 648.88, "duration": 3.959}, {"text": "didn't even know and the of an Anem of", "start": 650.92, "duration": 6.08}, {"text": "pledge is to reintegrate and re uh", "start": 652.839, "duration": 6.961}, {"text": "install if I can use that word the value", "start": 657.0, "duration": 4.959}, {"text": "that you should have as a citizen into", "start": 659.8, "duration": 4.64}, {"text": "you it's not for music see our new one", "start": 661.959, "duration": 4.601}, {"text": "now DJ something something they have put", "start": 664.44, "duration": 4.68}, {"text": "beats on it they they have cheapened it", "start": 666.56, "duration": 5.04}, {"text": "and that's what us we laughing at", "start": 669.12, "duration": 4.0}, {"text": "everything this nation that's what going", "start": 671.6, "duration": 4.4}, {"text": "to cost us don't get me wrong I laugh to", "start": 673.12, "duration": 4.6}, {"text": "I'm just saying ultimately our un", "start": 676.0, "duration": 4.44}, {"text": "seriousness may not cost us ultimately", "start": 677.72, "duration": 5.4}, {"text": "you understand what I'm saying so I", "start": 680.44, "duration": 7.24}, {"text": "believe that or let me now be H", "start": 683.12, "duration": 7.08}, {"text": "political that's my original believe my", "start": 687.68, "duration": 3.68}, {"text": "political belief is that we should have", "start": 690.2, "duration": 5.759}, {"text": "a mix of something that I don't see the", "start": 691.36, "duration": 6.44}, {"text": "work of Senate and House of", "start": 695.959, "duration": 5.761}, {"text": "rep if the president can pay you bribe", "start": 697.8, "duration": 5.4}, {"text": "you I'm not saying that's what happening", "start": 701.72, "duration": 2.72}, {"text": "in Nigeria I'm sure you understand I'm", "start": 703.2, "duration": 4.28}, {"text": "talking about uh my second country that", "start": 704.44, "duration": 6.28}, {"text": "I belong to by faith now if they can", "start": 707.48, "duration": 5.799}, {"text": "bribe you and do all that and you st", "start": 710.72, "duration": 3.96}, {"text": "whatever is doing whether it's good or", "start": 713.279, "duration": 4.0}, {"text": "is not good then your original Essence", "start": 714.68, "duration": 5.159}, {"text": "is lost the Senate was given to by the", "start": 717.279, "duration": 5.441}, {"text": "Romans and even the Emperors they fear", "start": 719.839, "duration": 4.24}, {"text": "the senate", "start": 722.72, "duration": 4.119}, {"text": "members because it's all about argument", "start": 724.079, "duration": 4.961}, {"text": "the arly agree among themselves and", "start": 726.839, "duration": 3.881}, {"text": "that's why they always put everything to", "start": 729.04, "duration": 3.96}, {"text": "a vote at the end of the day and all the", "start": 730.72, "duration": 6.28}, {"text": "Y and KN that we have so I would say we", "start": 733.0, "duration": 6.04}, {"text": "should sit as a nation and ask ourselves", "start": 737.0, "duration": 4.079}, {"text": "what are we practicing if I'm president", "start": 739.04, "duration": 4.52}, {"text": "are we capitalist are we communist are", "start": 741.079, "duration": 5.801}, {"text": "we an industrialized Nation are we uh in", "start": 743.56, "duration": 6.279}, {"text": "between are we a criminal Nation are we", "start": 746.88, "duration": 7.399}, {"text": "nations of TS uh ritualist kidnappers we", "start": 749.839, "duration": 6.041}, {"text": "should ask ourselves important questions", "start": 754.279, "duration": 4.401}, {"text": "now when we answer that democracy was", "start": 755.88, "duration": 6.0}, {"text": "formed by some people but it took them", "start": 758.68, "duration": 6.88}, {"text": "hundreds of years America is 10 times if", "start": 761.88, "duration": 6.319}, {"text": "not five times older than Nigeria so", "start": 765.56, "duration": 4.44}, {"text": "what they achieved over those period we", "start": 768.199, "duration": 4.76}, {"text": "can't achieve in 64 years so I think we", "start": 770.0, "duration": 4.92}, {"text": "should have found what worked for", "start": 772.959, "duration": 5.32}, {"text": "us disintegration and all that there are", "start": 774.92, "duration": 4.84}, {"text": "things you put on the table", "start": 778.279, "duration": 3.281}, {"text": "look at the Merit and the demerits I'm", "start": 779.76, "duration": 4.04}, {"text": "not in support of separating the country", "start": 781.56, "duration": 4.12}, {"text": "I've never been in support of that I've", "start": 783.8, "duration": 3.64}, {"text": "put it together for a reason but we need", "start": 785.68, "duration": 4.719}, {"text": "to ask ourselves what is the reason", "start": 787.44, "duration": 7.199}, {"text": "those are some things I will do", "start": 790.399, "duration": 7.12}, {"text": "differently political campaign politics", "start": 794.639, "duration": 5.601}, {"text": "should become something cheap if the", "start": 797.519, "duration": 5.641}, {"text": "Senate and House of re are going to all", "start": 800.24, "duration": 4.48}, {"text": "these nonsense offices that are useless", "start": 803.16, "duration": 2.96}, {"text": "all of them I'm talking to Nigeria", "start": 804.72, "duration": 4.2}, {"text": "directly I don't really care anymore if", "start": 806.12, "duration": 5.959}, {"text": "they are going to be functional then let", "start": 808.92, "duration": 6.52}, {"text": "them be civil servants put them on civil", "start": 812.079, "duration": 7.161}, {"text": "servant level you can't just be an idiot", "start": 815.44, "duration": 6.68}, {"text": "today poor miserable then you find your", "start": 819.24, "duration": 4.279}, {"text": "way into political office and you become", "start": 822.12, "duration": 3.24}, {"text": "a billionaire tomorrow it is not right", "start": 823.519, "duration": 3.801}, {"text": "it has destroyed the youth it has turned", "start": 825.36, "duration": 4.719}, {"text": "us into a cash society and it has also", "start": 827.32, "duration": 4.439}, {"text": "permitted the church because now people", "start": 830.079, "duration": 4.0}, {"text": "think once you broke you start a church", "start": 831.759, "duration": 4.601}, {"text": "church is a means to make", "start": 834.079, "duration": 6.2}, {"text": "money it is first uh what you see you", "start": 836.36, "duration": 5.839}, {"text": "see it everywhere is the Same Spirit you", "start": 840.279, "duration": 3.521}, {"text": "just Express itself in different", "start": 842.199, "duration": 3.44}, {"text": "dimension so if they are going to remain", "start": 843.8, "duration": 3.479}, {"text": "they should be civil servants their", "start": 845.639, "duration": 3.081}, {"text": "campaign can be done online they don't", "start": 847.279, "duration": 3.8}, {"text": "have to go to local government and all", "start": 848.72, "duration": 4.88}, {"text": "we can't have Technologies in this", "start": 851.079, "duration": 4.241}, {"text": "country where we load with child card", "start": 853.6, "duration": 4.359}, {"text": "once it's never used again we never Mis", "start": 855.32, "duration": 5.36}, {"text": "transferred money and when you m", "start": 857.959, "duration": 4.88}, {"text": "transferred you can reverse it and all", "start": 860.68, "duration": 3.399}, {"text": "that and we are saying we canot", "start": 862.839, "duration": 4.0}, {"text": "successfully hold an election that is", "start": 864.079, "duration": 5.521}, {"text": "electronic in nature somebody is", "start": 866.839, "duration": 5.401}, {"text": "somebody and as long as we are there it", "start": 869.6, "duration": 5.479}, {"text": "will not work so everybody everywhere", "start": 872.24, "duration": 4.88}, {"text": "that is registered as a voter you do", "start": 875.079, "duration": 4.2}, {"text": "retired card scratch it and load into", "start": 877.12, "duration": 5.76}, {"text": "the Sim I'm just using that as a analogy", "start": 879.279, "duration": 6.081}, {"text": "now Lo the Sim of your candidate and it", "start": 882.88, "duration": 4.959}, {"text": "is being seen on different screens in", "start": 885.36, "duration": 5.36}, {"text": "the country so as you are punching it is", "start": 887.839, "duration": 5.841}, {"text": "there instant result no whatever in as", "start": 890.72, "duration": 5.32}, {"text": "much as what you will do today they will", "start": 893.68, "duration": 4.719}, {"text": "upload it I mean you told us the machine", "start": 896.04, "duration": 4.239}, {"text": "will do all this and is doing the exact", "start": 898.399, "duration": 4.521}, {"text": "opposite so as to tell you the nation is", "start": 900.279, "duration": 6.0}, {"text": "set in such a way that it's a failed", "start": 902.92, "duration": 4.96}, {"text": "issue I know the president encouraged", "start": 906.279, "duration": 2.961}, {"text": "that we should be preaching and", "start": 907.88, "duration": 3.84}, {"text": "encouraging the nation the last time he", "start": 909.24, "duration": 4.68}, {"text": "gave H speech on one of the Christian", "start": 911.72, "duration": 5.16}, {"text": "whatever but I can't preach a lie I", "start": 913.92, "duration": 6.4}, {"text": "can't encourage people in a nation where", "start": 916.88, "duration": 5.24}, {"text": "the leaders where the law doesn't apply", "start": 920.32, "duration": 4.04}, {"text": "to people that have power but is the", "start": 922.12, "duration": 5.12}, {"text": "same law you you jail somebody for 5,000", "start": 924.36, "duration": 5.64}, {"text": "na he died in jail yet somebody for 5", "start": 927.24, "duration": 5.76}, {"text": "billion 2 billion 3 trillion is walking", "start": 930.0, "duration": 5.759}, {"text": "and roaming free you can't expect me to", "start": 933.0, "duration": 5.0}, {"text": "what will I preach even if you give me", "start": 935.759, "duration": 4.64}, {"text": "all the money in the world you can't", "start": 938.0, "duration": 4.48}, {"text": "still control that because I can't stand", "start": 940.399, "duration": 4.481}, {"text": "behind what is not right this is not", "start": 942.48, "duration": 4.52}, {"text": "about who has not sined before this is", "start": 944.88, "duration": 4.0}, {"text": "about the fact that it rises and falls", "start": 947.0, "duration": 5.56}, {"text": "with leadership if I'm running I can't", "start": 948.88, "duration": 5.04}, {"text": "tell you the plans I have I was the", "start": 952.56, "duration": 2.8}, {"text": "president if I was the president of this", "start": 953.92, "duration": 2.88}, {"text": "country there would be a lot of Debs", "start": 955.36, "duration": 4.44}, {"text": "first", "start": 956.8, "duration": 3.0}, {"text": "because that's that's the simple truth", "start": 960.36, "duration": 5.0}, {"text": "because I believe strongly that and I'm", "start": 962.92, "duration": 4.08}, {"text": "not saying there should be a revolution", "start": 965.36, "duration": 3.159}, {"text": "but if you punish people that are doing", "start": 967.0, "duration": 3.639}, {"text": "what is wrong it will all this are", "start": 968.519, "duration": 3.481}, {"text": "shouting the youths are jobless the", "start": 970.639, "duration": 4.56}, {"text": "youths are criminal in nature can senat", "start": 972.0, "duration": 5.72}, {"text": "that he's a criminal himself can a thief", "start": 975.199, "duration": 7.161}, {"text": "call just like say is a thief it's not", "start": 977.72, "duration": 7.359}, {"text": "right so why I'm not justifying the boys", "start": 982.36, "duration": 5.52}, {"text": "stealing and doing internet fraud but", "start": 985.079, "duration": 4.44}, {"text": "you that you also stealing with pen and", "start": 987.88, "duration": 3.68}, {"text": "paper like fella said many years back", "start": 989.519, "duration": 4.601}, {"text": "you can't you can't cast a stone towards", "start": 991.56, "duration": 4.68}, {"text": "them so I believe we should collapse", "start": 994.12, "duration": 4.159}, {"text": "everything and start all over again I", "start": 996.24, "duration": 4.079}, {"text": "know that Min of jat tried to do", "start": 998.279, "duration": 4.92}, {"text": "National confab and all that even though", "start": 1000.319, "duration": 6.32}, {"text": "we didn't see the report among other", "start": 1003.199, "duration": 5.401}, {"text": "things so maybe that's what is needed", "start": 1006.639, "duration": 4.68}, {"text": "sincere one and let's but the people", "start": 1008.6, "duration": 6.599}, {"text": "Cashing Out can't lose their way of life", "start": 1011.319, "duration": 6.241}, {"text": "so the motto now is just find your way", "start": 1015.199, "duration": 4.361}, {"text": "into that Circle so that your own two", "start": 1017.56, "duration": 3.24}, {"text": "can be guaranteed and those are the", "start": 1019.56, "duration": 3.48}, {"text": "things that we that we need to change or", "start": 1020.8, "duration": 4.72}, {"text": "that we aim to change as a president now", "start": 1023.04, "duration": 4.279}, {"text": "like I said there are parts of", "start": 1025.52, "duration": 4.039}, {"text": "leadership especially of this nation", "start": 1027.319, "duration": 5.041}, {"text": "that you don't know that I don't know", "start": 1029.559, "duration": 4.961}, {"text": "but when we get there I can't believe", "start": 1032.36, "duration": 3.079}, {"text": "even though we don't know what the", "start": 1034.52, "duration": 3.039}, {"text": "problem is I can't believe we can't find", "start": 1035.439, "duration": 5.12}, {"text": "a solution to that problem because", "start": 1037.559, "duration": 5.841}, {"text": "Nigeria is so blessed I mean we've had", "start": 1040.559, "duration": 5.28}, {"text": "the president that he's dead he Pi even", "start": 1043.4, "duration": 5.8}, {"text": "though he's dead still sending us money", "start": 1045.839, "duration": 5.321}, {"text": "every time that's to tell you the vast", "start": 1049.2, "duration": 5.04}, {"text": "wealth that is in this country and if we", "start": 1051.16, "duration": 5.72}, {"text": "keep running to for foreign AIDS and all", "start": 1054.24, "duration": 5.52}, {"text": "that you can't do well the nation nigia", "start": 1056.88, "duration": 4.72}, {"text": "should not be taking money from anybody", "start": 1059.76, "duration": 3.08}, {"text": "we actually should be the one borrowing", "start": 1061.6, "duration": 4.0}, {"text": "money to other African nations uh and", "start": 1062.84, "duration": 6.28}, {"text": "all that but like I said that's just", "start": 1065.6, "duration": 5.88}, {"text": "when I sleep those are what I dream it's", "start": 1069.12, "duration": 3.48}, {"text": "just a", "start": 1071.48, "duration": 5.28}, {"text": "dream it's not I'm not saying that's", "start": 1072.6, "duration": 6.84}, {"text": "what should be done like taxes", "start": 1076.76, "duration": 4.0}, {"text": "they can be done", "start": 1079.44, "duration": 4.0}, {"text": "right they can be done right that", "start": 1080.76, "duration": 5.399}, {"text": "everybody will pay once it's clear every", "start": 1083.44, "duration": 4.84}, {"text": "law is shouted in Myster so there will", "start": 1086.159, "duration": 4.321}, {"text": "always be room for all kinds of things", "start": 1088.28, "duration": 4.879}, {"text": "but if I tell you your salary is 50,000", "start": 1090.48, "duration": 4.72}, {"text": "this is your tax it's clear so if you", "start": 1093.159, "duration": 5.721}, {"text": "get into it's even electronically done", "start": 1095.2, "duration": 5.88}, {"text": "now so you need to go is the people in", "start": 1098.88, "duration": 4.32}, {"text": "the back office just be handling paper", "start": 1101.08, "duration": 3.52}, {"text": "you go there they should not have access", "start": 1103.2, "duration": 3.32}, {"text": "to anything other than paper you go", "start": 1104.6, "duration": 5.4}, {"text": "there you click 50,000 you pay what it", "start": 1106.52, "duration": 4.92}, {"text": "comes out automatic pay what you need to", "start": 1110.0, "duration": 2.96}, {"text": "pay now how do you know the person is", "start": 1111.44, "duration": 3.08}, {"text": "telling the truth that is where", "start": 1112.96, "duration": 3.079}, {"text": "automating Banks and all those things", "start": 1114.52, "duration": 5.039}, {"text": "that's where they come in so my my bank", "start": 1116.039, "duration": 6.281}, {"text": "is connected directly if money comes", "start": 1119.559, "duration": 4.36}, {"text": "deliver salary I can't say it's not my", "start": 1122.32, "duration": 4.12}, {"text": "salary so it's set up such way that", "start": 1123.919, "duration": 4.721}, {"text": "salary is 200,000 as his land in the", "start": 1126.44, "duration": 4.76}, {"text": "back is removing automatically what", "start": 1128.64, "duration": 5.0}, {"text": "should be the tax of it it's not", "start": 1131.2, "duration": 5.599}, {"text": "English citizens companies they pay tax", "start": 1133.64, "duration": 6.519}, {"text": "the same way uh in CES we pay offerings", "start": 1136.799, "duration": 5.921}, {"text": "and tis and all that so many things but", "start": 1140.159, "duration": 5.0}, {"text": "let Nigeria matter we pray for Nigeria", "start": 1142.72, "duration": 6.12}, {"text": "and hopefully one day God will help us", "start": 1145.159, "duration": 7.321}, {"text": "60,000 we are still debating and all", "start": 1148.84, "duration": 6.959}, {"text": "that but what can 60,000 really do in", "start": 1152.48, "duration": 5.28}, {"text": "today's", "start": 1155.799, "duration": 6.561}, {"text": "economy so last question", "start": 1157.76, "duration": 4.6}, {"text": "[Applause]", "start": 1163.77, "duration": 3.589}, {"text": "[Music]", "start": 1168.23, "duration": 8.78}, {"text": "[Applause]", "start": 1170.97, "duration": 11.299}, {"text": "[Music]", "start": 1177.01, "duration": 5.259}]